lazysequence/__init__.py
lazysequence/py.typed
lazysequence-0.3.0.dist-info/LICENSE.rst
lazysequence-0.3.0.dist-info/WHEEL
lazysequence-0.3.0.dist-info/METADATA
lazysequence-0.3.0.dist-info/RECORD
