Metadata-Version: 2.1
Name: lazysequence
Version: 0.3.0
Summary: lazysequence
Home-page: https://github.com/cjolowicz/lazysequence
License: MIT
Author: Claudio Jolowicz
Author-email: mail@claudiojolowicz.com
Requires-Python: >=3.7,<4.0
Classifier: Development Status :: 3 - Alpha
Classifier: License :: OSI Approved :: MIT License
Classifier: Programming Language :: Python :: 3
Classifier: Programming Language :: Python :: 3.7
Classifier: Programming Language :: Python :: 3.8
Classifier: Programming Language :: Python :: 3.9
Project-URL: Changelog, https://github.com/cjolowicz/lazysequence/releases
Project-URL: Documentation, https://lazysequence.readthedocs.io
Project-URL: Repository, https://github.com/cjolowicz/lazysequence
